{
  "data": {
    "triggers": {
      "list": [
        {
          "actions": [
            {
              "__OBJ_TYPE": "Action_SetEntityPosition",
              "components": [
                {
                  "__OBJ_TYPE": "Component_Params",
                  "params": [
                    {
                      "value": {
                        "__OBJ_TYPE": "T_Entity",
                        "action": "db65e90a-68d9-43de-9b56-b9da69280d5e"
                      }
                    },
                    {
                      "value": {
                        "__OBJ_TYPE": "T_Map",
                        "rawval": "b370a9ff-36b6-479d-a1b9-2f8f6200d516"
                      }
                    },
                    {
                      "value": {
                        "__OBJ_TYPE": "T_ScenePos",
                        "rawval": {
                          "pos": {
                            "x": -4,
                            "y": 1,
                            "z": -45
                          }
                        }
                      }
                    },
                    {
                      "value": {
                        "__OBJ_TYPE": "T_Int"
                      }
                    },
                    {
                      "value": {
                        "__OBJ_TYPE": "T_Int"
                      }
                    }
                  ]
                }
              ],
              "id": {
                "value": "955c62aa-49d2-43d4-a991-83cfda3f6faa"
              },
              "pos": {
                "x": 827,
                "y": 344
              }
            },
            {
              "__OBJ_TYPE": "Action_GetContextVar",
              "components": [
                {
                  "__OBJ_TYPE": "Component_Context",
                  "key": "obj2"
                }
              ],
              "id": {
                "value": "db65e90a-68d9-43de-9b56-b9da69280d5e"
              },
              "pos": {
                "x": 1540,
                "y": 358
              },
              "type": "T_Entity"
            }
          ],
          "custom_trigger_data": {
            "name": {
              "value": "ab6dcdbb-0bc2-405c-90b7-bada57d9ead0"
            },
            "type": "Trigger_PartTouchEntityBegin"
          },
          "root": {
            "components": [
              {
                "__OBJ_TYPE": "Component_Sequence",
                "children": [
                  {
                    "action": "955c62aa-49d2-43d4-a991-83cfda3f6faa"
                  }
                ]
              }
            ],
            "id": {
              "value": "d6150b7c-4287-45c6-908a-84d5864d4d17"
            }
          },
          "type": "Trigger_PartTouchEntityBegin"
        }
      ]
    }
  },
  "meta": {
    "EXPORT": {
      "triggers.bts": "4670a592c9760320d012147570bb2f12"
    },
    "VERSION": "0.21"
  }
}